LICENSE
MANIFEST.in
README.rst
setup.py
khl_team/__init__.py
khl_team/exceptions.py
khl_team/khl.py
khl_team/parser.py
khl_team.egg-info/PKG-INFO
khl_team.egg-info/SOURCES.txt
khl_team.egg-info/dependency_links.txt
khl_team.egg-info/requires.txt
khl_team.egg-info/top_level.txt