Metadata-Version: 1.1
Name: khl-team
Version: 1.0
Summary: Interface for obtaining data about KHL teams
Home-page: https://github.com/artcom-net/khl-team
Author: Artem Kustov
Author-email: artem.kustov@artcom-net.ru
License: MIT
Platform: UNKNOWN
Classifier: Development Status :: 5 - Production/Stable
Classifier: Intended Audience :: Developers
Classifier: License :: OSI Approved :: MIT License
Classifier: Operating System :: OS Independent
Classifier: Programming Language :: Python :: 3 :: Only
Classifier: Topic :: Text Processing :: Markup :: HTML
Classifier: Topic :: Utilities
